<?xml version="1.0" encoding="utf-8"?>
<?xml-stylesheet type="text/xsl" href="CCD.xsl"?>
<!--Copyright EXACTDATA, LLC. ALL RIGHTS RESERVED.-->
<!--This file contains synthetic data depicting a fictional health summary. Any resemblance to a real person is coincidental.-->
<ClinicalDocument xmlns:xsi="http://www.w3.org/2001/XMLSchema-instance" xsi:schemaLocation="urn:hl7-org:v3 http://xreg2.nist.gov:8080/hitspValidation/schema/cdar2c32/infrastructure/cda/C32_CDA.xsd" xmlns="urn:hl7-org:v3">
  <realmCode code="US" />
  <typeId root="2.16.840.1.113883.1.3" extension="POCD_HD000040" />
  <templateId root="2.16.840.1.113883.10.20.3" />
  <templateId root="1.3.6.1.4.1.19376.1.5.3.1.1.1" />
  <templateId root="2.16.840.1.113883.3.88.11.32.1" assigningAuthorityName="HITSP/C32" />
  <id root="783BDB4C-E60A-4B84-8BDE-91FAB5B80130" />
  <code code="34133-9" codeSystem="2.16.840.1.113883.6.1" displayName="Summarization of episode note" />
  <title>Continuity of Care Document</title>
  <effectiveTime value="20121106200000" />
  <confidentialityCode code="N" codeSystem="2.16.840.1.113883.5.25" />
  <languageCode code="en-US" />
  <recordTarget>
    <patientRole>
      <!--Patient ID 576003952-01-->
      <id extension="576-00-3952" root="2.16.840.1.113883.4.1" />
      <addr use="HP">
        <streetAddressLine>8843 North Valley Road</streetAddressLine>
        <city>Chautauqua</city>
        <state>NY</state>
        <postalCode>14722</postalCode>
      </addr>
      <telecom value="tel:+1-281-305-9185" use="HP" />
      <patient>
        <name>
          <given>Gwendolyn</given>
          <given>R</given>
          <family>Ryan</family>
        </name>
        <administrativeGenderCode code="F" displayName="Female" codeSystemName="HL7 AdministrativeGenderCodes" codeSystem="2.16.840.1.113883.5.1" />
        <birthTime value="19630725" />
        <maritalStatusCode code="D" displayName="Divorced" codeSystem="2.16.840.1.113883.5.2" codeSystemName="MaritalStatusCode" />
        <raceCode displayName="White" code="2106-3" codeSystem="2.16.840.1.113883.6.238" codeSystemName="CDC Race and Ethnicity" />
        <languageCommunication>
          <templateId root="1.3.6.1.4.1.19376.1.5.3.1.2.1" assigningAuthorityName="IHE PCC" />
          <templateId root="2.16.840.1.113883.3.88.11.83.2" assigningAuthorityName="HITSP C83" />
          <languageCode code="en-US" />
          <preferenceInd value="true" />
        </languageCommunication>
      </patient>
    </patientRole>
  </recordTarget>
  <author>
    <time value="20121106200000" />
    <assignedAuthor>
      <id extension="1897987945" root="2.16.840.1.113883.4.6" />
      <addr use="WP">
        <streetAddressLine>6321 Lacey Drive</streetAddressLine>
        <city>Lakewood</city>
        <state>NY</state>
        <postalCode>14750</postalCode>
      </addr>
      <telecom value="tel:+1-504-692-1745" use="WP" />
      <assignedPerson>
        <realmCode code="US" />
        <name>
          <given>Gisela</given>
          <family>Griffin</family>
          <suffix>MD</suffix>
        </name>
      </assignedPerson>
      <representedOrganization>
        <id root="2.16.840.1.113883.4.450" />
        <name>ExactData County Medical Center</name>
        <telecom use="WP" nullFlavor="UNK" />
        <addr use="WP" nullFlavor="UNK" />
      </representedOrganization>
    </assignedAuthor>
  </author>
  <custodian>
    <assignedCustodian>
      <representedCustodianOrganization>
        <id root="2.16.840.1.113883.4.450" />
        <name>ExactData County Medical Center</name>
        <telecom use="WP" nullFlavor="UNK" />
        <addr use="WP" nullFlavor="UNK" />
      </representedCustodianOrganization>
    </assignedCustodian>
  </custodian>
  <participant typeCode="IND">
    <templateId root="2.16.840.1.113883.3.88.11.83.3" />
    <templateId root="1.3.6.1.4.1.19376.1.5.3.1.2.4" />
    <time value="20121106200000" />
    <associatedEntity classCode="ECON">
      <code code="FRND" displayName="unrelated friend" codeSystem="2.16.840.1.113883.5.111" codeSystemName="RoleCode" />
      <addr />
      <telecom value="tel:+1-805-367-9107" use="HP" />
      <associatedPerson>
        <name>
          <given>Ahmed</given>
          <family>Rowe</family>
        </name>
      </associatedPerson>
    </associatedEntity>
  </participant>
  <documentationOf>
    <serviceEvent classCode="PCPR">
      <effectiveTime>
        <low value="20121106200000" />
        <high value="20121106200000" />
      </effectiveTime>
      <performer typeCode="PRF">
        <templateId root="2.16.840.1.113883.3.88.11.83.4" />
        <templateId root="1.3.6.1.4.1.19376.1.5.3.1.2.3" />
        <functionCode code="PP" displayName="Primary Care Provider" codeSystem="2.16.840.1.113883.12.443" codeSystemName="Provider Role">
          <originalText>Primary Care Provider</originalText>
        </functionCode>
        <time>
          <low value="20121031131500" />
          <high value="20121031131500" />
        </time>
        <assignedEntity>
          <id extension="1897987945" root="2.16.840.1.113883.4.6" />
          <code code="200000000X" displayName="Allopathic &amp; Osteopathic Physicians" codeSystem="2.16.840.1.113883.6.101" codeSystemName="NUCC Provider Codes" />
          <addr use="WP">
            <streetAddressLine>6321 Lacey Drive</streetAddressLine>
            <city>Lakewood</city>
            <state>NY</state>
            <postalCode>14750</postalCode>
          </addr>
          <telecom value="tel:+1-504-692-1745" use="WP" />
          <assignedPerson>
            <realmCode code="US" />
            <name>
              <given>Gisela</given>
              <family>Griffin</family>
              <suffix>MD</suffix>
            </name>
          </assignedPerson>
          <representedOrganization>
            <id root="2.16.840.1.113883.4.450" />
            <name>ExactData County Medical Center</name>
            <telecom use="WP" nullFlavor="UNK" />
            <addr use="WP" nullFlavor="UNK" />
          </representedOrganization>
        </assignedEntity>
      </performer>
      <performer typeCode="PRF">
        <templateId root="2.16.840.1.113883.3.88.11.83.4" />
        <templateId root="1.3.6.1.4.1.19376.1.5.3.1.2.3" />
        <functionCode code="PP" displayName="Primary Care Provider" codeSystem="2.16.840.1.113883.12.443" codeSystemName="Provider Role">
          <originalText>Primary Care Provider</originalText>
        </functionCode>
        <time>
          <low value="20121106200000" />
          <high value="20121106200000" />
        </time>
        <assignedEntity>
          <id extension="2648971345" root="2.16.840.1.113883.4.6" />
          <code code="200000000X" displayName="Allopathic &amp; Osteopathic Physicians" codeSystem="2.16.840.1.113883.6.101" codeSystemName="NUCC Provider Codes" />
          <addr use="WP">
            <streetAddressLine>6410 North Pine Street</streetAddressLine>
            <city>Silver Creek</city>
            <state>NY</state>
            <postalCode>14136</postalCode>
          </addr>
          <telecom value="tel:+1-619-624-5122" use="WP" />
          <assignedPerson>
            <realmCode code="US" />
            <name>
              <given>Ryan</given>
              <family>Quinn</family>
              <suffix></suffix>
            </name>
          </assignedPerson>
          <representedOrganization>
            <id root="2.16.840.1.113883.4.450" />
            <name>ExactData County Medical Center</name>
            <telecom use="WP" nullFlavor="UNK" />
            <addr use="WP" nullFlavor="UNK" />
          </representedOrganization>
        </assignedEntity>
      </performer>
    </serviceEvent>
  </documentationOf>
  <component>
    <structuredBody>
      <component>
        <!--Purpose section-->
        <section>
          <templateId root="2.16.840.1.113883.10.20.1.13" />
          <!--Purpose section template-->
          <code code="48764-5" displayName="Purpose" codeSystem="2.16.840.1.113883.6.1" />
          <title>Summary of Purpose</title>
          <text>Transfer of care</text>
          <entry typeCode="DRIV">
            <act classCode="ACT" moodCode="EVN">
              <templateId root="2.16.840.1.113883.10.20.1.30" />
              <!--Purpose activity template-->
              <code code="23745001" codeSystem="2.16.840.1.113883.6.96" displayName="Documentation procedure" />
              <statusCode code="completed" />
              <entryRelationship typeCode="RSON">
                <act classCode="ACT" moodCode="EVN">
                  <code code="308292007" codeSystem="2.16.840.1.113883.6.96" displayName="Transfer of care" />
                  <statusCode code="completed" />
                </act>
              </entryRelationship>
            </act>
          </entry>
        </section>
      </component>
      <component>
        <!--Results Section-->
        <section>
          <templateId root="2.16.840.1.113883.3.88.11.83.122" assigningAuthorityName="HITSP/C83" />
          <templateId root="1.3.6.1.4.1.19376.1.5.3.1.3.28" assigningAuthorityName="IHE PCC" />
          <templateId root="2.16.840.1.113883.10.20.1.14" assigningAuthorityName="CCD" />
          <code code="30954-2" displayName="Relevant diagnostic tests and/or laboratory data" codeSystem="2.16.840.1.113883.6.1" codeSystemName="LOINC" />
          <title>Results</title>
          <text>
            <table border="1" width="100%">
              <thead>
                <tr>
                  <th>Test</th>
                  <th>Result</th>
                  <th>Preformer</th>
                  <th>Date Collected</th>
                  <th>Date Resulted</th>
                </tr>
              </thead>
              <tbody>
                <tr>
                  <td>
                    <content ID="result-1">Comprehensive Metabolic Panel</content>
                  </td>
                  <td>
                    <content ID="result-1_1_1">ALP=220 U/L</content>,<content ID="result-1_12">AST=25 U/L</content>,<content ID="result-1_13">ALT=25 U/L</content>,<content ID="result-1_14">Total Bilirubin=3.5 mg/dL</content></td>
                  <td>Young Health Labs</td>
                  <td>2012-11-06T20:00:00Z</td>
                  <td>2012-11-07T01:55:28Z</td>
                </tr>
                <tr>
                  <td>
                    <content ID="result-2">Amylase</content>
                  </td>
                  <td>
                    <content ID="result-2_2_1">Amylase=145 U/L</content>
                  </td>
                  <td>Young Health Labs</td>
                  <td>2012-11-06T20:00:00Z</td>
                  <td>2012-11-06T23:00:06Z</td>
                </tr>
                <tr>
                  <td>
                    <content ID="result-3">Lipase</content>
                  </td>
                  <td>
                    <content ID="result-3_3_1">Lipase=100 U/L</content>
                  </td>
                  <td>Young Health Labs</td>
                  <td>2012-11-06T20:00:00Z</td>
                  <td>2012-11-06T22:16:40Z</td>
                </tr>
                <tr>
                  <td>
                    <content ID="result-4">CA 19-9</content>
                  </td>
                  <td>
                    <content ID="result-4_4_1">CA 19-9=120 U/mL</content>
                  </td>
                  <td>Young Health Labs</td>
                  <td>2012-11-06T20:00:00Z</td>
                  <td>2012-11-07T01:26:50Z</td>
                </tr>
              </tbody>
            </table>
          </text>
          <entry typeCode="COMP">
            <organizer classCode="BATTERY" moodCode="EVN">
              <templateId root="2.16.840.1.113883.10.20.1.32" assigningAuthorityName="CCD" />
              <id root="2.16.840.1.113883.4.450" extension="121106 CH 22183906" />
              <code codeSystem="2.16.840.1.113883.6.1" codeSystemName="LOINC" code="24323-8" displayName="Comprehensive Metabolic Panel" />
              <statusCode code="completed" />
              <component>
                <procedure classCode="PROC" moodCode="EVN">
                  <templateId root="2.16.840.1.113883.3.88.11.83.17" assigningAuthorityName="HITSP C83" />
                  <templateId root="2.16.840.1.113883.10.20.1.29" assigningAuthorityName="CCD" />
                  <templateId root="1.3.6.1.4.1.19376.1.5.3.1.4.19" assigningAuthorityName="IHE PCC" />
                  <!--Result procedure observation template-->
                  <id root="639C7E08-2CE7-4146-8278-42D6BBC4B3DC" />
                  <code codeSystem="2.16.840.1.113883.6.1" codeSystemName="LOINC" code="24323-8" displayName="Comprehensive Metabolic Panel">
                    <originalText>
                      <reference value="#result-1" />
                    </originalText>
                  </code>
                  <text>
                    <reference value="#result-1" />
                  </text>
                  <statusCode code="completed" />
                  <effectiveTime value="20121106200000" />
                  <performer typeCode="PRF">
                    <time>
                      <high value="20121106200000" />
                    </time>
                    <assignedEntity>
                      <id extension="703927546" root="2.16.840.1.113883.4.450" />
                      <addr use="WP">
                        <streetAddressLine>6410 North Pine Street</streetAddressLine>
                        <city>Silver Creek</city>
                        <state>NY</state>
                        <postalCode>14136</postalCode>
                      </addr>
                      <telecom value="tel:+1-619-624-5122" use="WP" />
                      <assignedPerson>
                        <realmCode code="US" />
                        <name>
                          <given>Ryan</given>
                          <family>Quinn</family>
                          <suffix></suffix>
                        </name>
                      </assignedPerson>
                      <representedOrganization>
                        <id nullFlavor="UNK" />
                        <name>Young Health Labs</name>
                        <telecom use="WP" value="tel:+1-619-624-5122" />
                        <addr use="WP">
                          <streetAddressLine>6410 North Pine Street</streetAddressLine>
                          <city>Silver Creek</city>
                          <state>NY</state>
                          <postalCode>14136</postalCode>
                        </addr>
                      </representedOrganization>
                    </assignedEntity>
                  </performer>
                </procedure>
              </component>
              <component>
                <observation classCode="OBS" moodCode="EVN">
                  <templateId root="2.16.840.1.113883.3.88.11.83.15.1" assigningAuthorityName="HITSP C83" />
                  <templateId root="2.16.840.1.113883.10.20.1.31" assigningAuthorityName="CCD" />
                  <templateId root="1.3.6.1.4.1.19376.1.5.3.1.4.13" assigningAuthorityName="IHE PCC" />
                  <!--Result observation template-->
                  <id root="09D09902-0548-493F-80C1-EEB33BB65E27" />
                  <code code="6768-6" displayName="ALP" codeSystem="2.16.840.1.113883.6.1" codeSystemName="LOINC" />
                  <text>
                    <reference value="#result-1_1_1" />
                  </text>
                  <statusCode code="completed" />
                  <effectiveTime value="20121107015528" />
                  <value xsi:type="PQ" value="220" unit="U/L" />
                </observation>
              </component>
              <component>
                <observation classCode="OBS" moodCode="EVN">
                  <templateId root="2.16.840.1.113883.3.88.11.83.15.1" assigningAuthorityName="HITSP C83" />
                  <templateId root="2.16.840.1.113883.10.20.1.31" assigningAuthorityName="CCD" />
                  <templateId root="1.3.6.1.4.1.19376.1.5.3.1.4.13" assigningAuthorityName="IHE PCC" />
                  <!--Result observation template-->
                  <id root="E2EBD1C1-C6B8-4189-834C-3685185EE0E8" />
                  <code code="1920-8" displayName="AST" codeSystem="2.16.840.1.113883.6.1" codeSystemName="LOINC" />
                  <text>
                    <reference value="#result-2_1_2" />
                  </text>
                  <statusCode code="completed" />
                  <effectiveTime value="20121107015528" />
                  <value xsi:type="PQ" value="25" unit="U/L" />
                </observation>
              </component>
              <component>
                <observation classCode="OBS" moodCode="EVN">
                  <templateId root="2.16.840.1.113883.3.88.11.83.15.1" assigningAuthorityName="HITSP C83" />
                  <templateId root="2.16.840.1.113883.10.20.1.31" assigningAuthorityName="CCD" />
                  <templateId root="1.3.6.1.4.1.19376.1.5.3.1.4.13" assigningAuthorityName="IHE PCC" />
                  <!--Result observation template-->
                  <id root="6F2E94CE-9D3B-4B85-89BB-D6B4FB88CC5F" />
                  <code code="1742-6" displayName="ALT" codeSystem="2.16.840.1.113883.6.1" codeSystemName="LOINC" />
                  <text>
                    <reference value="#result-3_1_3" />
                  </text>
                  <statusCode code="completed" />
                  <effectiveTime value="20121107015528" />
                  <value xsi:type="PQ" value="25" unit="U/L" />
                </observation>
              </component>
              <component>
                <observation classCode="OBS" moodCode="EVN">
                  <templateId root="2.16.840.1.113883.3.88.11.83.15.1" assigningAuthorityName="HITSP C83" />
                  <templateId root="2.16.840.1.113883.10.20.1.31" assigningAuthorityName="CCD" />
                  <templateId root="1.3.6.1.4.1.19376.1.5.3.1.4.13" assigningAuthorityName="IHE PCC" />
                  <!--Result observation template-->
                  <id root="472C82E6-11AF-4C3A-899E-2943BCD0985D" />
                  <code code="1975-2" displayName="Total Bilirubin" codeSystem="2.16.840.1.113883.6.1" codeSystemName="LOINC" />
                  <text>
                    <reference value="#result-4_1_4" />
                  </text>
                  <statusCode code="completed" />
                  <effectiveTime value="20121107015528" />
                  <value xsi:type="PQ" value="3.5" unit="mg/dL" />
                </observation>
              </component>
            </organizer>
          </entry>
          <entry typeCode="COMP">
            <organizer classCode="CLUSTER" moodCode="EVN">
              <templateId root="2.16.840.1.113883.10.20.1.32" assigningAuthorityName="CCD" />
              <id root="2.16.840.1.113883.4.450" extension="121106 CH 73107751" />
              <code codeSystem="2.16.840.1.113883.6.1" codeSystemName="LOINC" code="1798-8" displayName="Amylase" />
              <statusCode code="completed" />
              <component>
                <procedure classCode="PROC" moodCode="EVN">
                  <templateId root="2.16.840.1.113883.3.88.11.83.17" assigningAuthorityName="HITSP C83" />
                  <templateId root="2.16.840.1.113883.10.20.1.29" assigningAuthorityName="CCD" />
                  <templateId root="1.3.6.1.4.1.19376.1.5.3.1.4.19" assigningAuthorityName="IHE PCC" />
                  <!--Result procedure observation template-->
                  <id root="DBCC8610-32A9-489F-8BF8-242B10734009" />
                  <code codeSystem="2.16.840.1.113883.6.1" codeSystemName="LOINC" code="1798-8" displayName="Amylase">
                    <originalText>
                      <reference value="#result-5" />
                    </originalText>
                  </code>
                  <text>
                    <reference value="#result-5" />
                  </text>
                  <statusCode code="completed" />
                  <effectiveTime value="20121106200000" />
                  <performer typeCode="PRF">
                    <time>
                      <high value="20121106200000" />
                    </time>
                    <assignedEntity>
                      <id extension="703927546" root="2.16.840.1.113883.4.450" />
                      <addr use="WP">
                        <streetAddressLine>6410 North Pine Street</streetAddressLine>
                        <city>Silver Creek</city>
                        <state>NY</state>
                        <postalCode>14136</postalCode>
                      </addr>
                      <telecom value="tel:+1-619-624-5122" use="WP" />
                      <assignedPerson>
                        <realmCode code="US" />
                        <name>
                          <given>Ryan</given>
                          <family>Quinn</family>
                          <suffix></suffix>
                        </name>
                      </assignedPerson>
                      <representedOrganization>
                        <id nullFlavor="UNK" />
                        <name>Young Health Labs</name>
                        <telecom use="WP" value="tel:+1-619-624-5122" />
                        <addr use="WP">
                          <streetAddressLine>6410 North Pine Street</streetAddressLine>
                          <city>Silver Creek</city>
                          <state>NY</state>
                          <postalCode>14136</postalCode>
                        </addr>
                      </representedOrganization>
                    </assignedEntity>
                  </performer>
                </procedure>
              </component>
              <component>
                <observation classCode="OBS" moodCode="EVN">
                  <templateId root="2.16.840.1.113883.3.88.11.83.15.1" assigningAuthorityName="HITSP C83" />
                  <templateId root="2.16.840.1.113883.10.20.1.31" assigningAuthorityName="CCD" />
                  <templateId root="1.3.6.1.4.1.19376.1.5.3.1.4.13" assigningAuthorityName="IHE PCC" />
                  <!--Result observation template-->
                  <id root="2677B758-DD95-4AA4-89C2-E726BE1AE2BA" />
                  <code code="1798-8" displayName="Amylase" codeSystem="2.16.840.1.113883.6.1" codeSystemName="LOINC" />
                  <text>
                    <reference value="#result-5_2_1" />
                  </text>
                  <statusCode code="completed" />
                  <effectiveTime value="20121106230006" />
                  <value xsi:type="PQ" value="145" unit="U/L" />
                </observation>
              </component>
            </organizer>
          </entry>
          <entry typeCode="COMP">
            <organizer classCode="CLUSTER" moodCode="EVN">
              <templateId root="2.16.840.1.113883.10.20.1.32" assigningAuthorityName="CCD" />
              <id root="2.16.840.1.113883.4.450" extension="121106 CH 97106452" />
              <code codeSystem="2.16.840.1.113883.6.1" codeSystemName="LOINC" code="3040-3" displayName="Lipase" />
              <statusCode code="completed" />
              <component>
                <procedure classCode="PROC" moodCode="EVN">
                  <templateId root="2.16.840.1.113883.3.88.11.83.17" assigningAuthorityName="HITSP C83" />
                  <templateId root="2.16.840.1.113883.10.20.1.29" assigningAuthorityName="CCD" />
                  <templateId root="1.3.6.1.4.1.19376.1.5.3.1.4.19" assigningAuthorityName="IHE PCC" />
                  <!--Result procedure observation template-->
                  <id root="961F38EE-1725-4495-86D1-014893D7228B" />
                  <code codeSystem="2.16.840.1.113883.6.1" codeSystemName="LOINC" code="3040-3" displayName="Lipase">
                    <originalText>
                      <reference value="#result-6" />
                    </originalText>
                  </code>
                  <text>
                    <reference value="#result-6" />
                  </text>
                  <statusCode code="completed" />
                  <effectiveTime value="20121106200000" />
                  <performer typeCode="PRF">
                    <time>
                      <high value="20121106200000" />
                    </time>
                    <assignedEntity>
                      <id extension="703927546" root="2.16.840.1.113883.4.450" />
                      <addr use="WP">
                        <streetAddressLine>6410 North Pine Street</streetAddressLine>
                        <city>Silver Creek</city>
                        <state>NY</state>
                        <postalCode>14136</postalCode>
                      </addr>
                      <telecom value="tel:+1-619-624-5122" use="WP" />
                      <assignedPerson>
                        <realmCode code="US" />
                        <name>
                          <given>Ryan</given>
                          <family>Quinn</family>
                          <suffix></suffix>
                        </name>
                      </assignedPerson>
                      <representedOrganization>
                        <id nullFlavor="UNK" />
                        <name>Young Health Labs</name>
                        <telecom use="WP" value="tel:+1-619-624-5122" />
                        <addr use="WP">
                          <streetAddressLine>6410 North Pine Street</streetAddressLine>
                          <city>Silver Creek</city>
                          <state>NY</state>
                          <postalCode>14136</postalCode>
                        </addr>
                      </representedOrganization>
                    </assignedEntity>
                  </performer>
                </procedure>
              </component>
              <component>
                <observation classCode="OBS" moodCode="EVN">
                  <templateId root="2.16.840.1.113883.3.88.11.83.15.1" assigningAuthorityName="HITSP C83" />
                  <templateId root="2.16.840.1.113883.10.20.1.31" assigningAuthorityName="CCD" />
                  <templateId root="1.3.6.1.4.1.19376.1.5.3.1.4.13" assigningAuthorityName="IHE PCC" />
                  <!--Result observation template-->
                  <id root="047E1B3F-1D11-47F4-8F04-8B20035E6FE3" />
                  <code code="3040-3" displayName="Lipase" codeSystem="2.16.840.1.113883.6.1" codeSystemName="LOINC" />
                  <text>
                    <reference value="#result-6_3_1" />
                  </text>
                  <statusCode code="completed" />
                  <effectiveTime value="20121106221640" />
                  <value xsi:type="PQ" value="100" unit="U/L" />
                </observation>
              </component>
            </organizer>
          </entry>
          <entry typeCode="COMP">
            <organizer classCode="CLUSTER" moodCode="EVN">
              <templateId root="2.16.840.1.113883.10.20.1.32" assigningAuthorityName="CCD" />
              <id root="2.16.840.1.113883.4.450" extension="121106 CH 18700346" />
              <code codeSystem="2.16.840.1.113883.6.1" codeSystemName="LOINC" code="24108-3" displayName="CA 19-9" />
              <statusCode code="completed" />
              <component>
                <procedure classCode="PROC" moodCode="EVN">
                  <templateId root="2.16.840.1.113883.3.88.11.83.17" assigningAuthorityName="HITSP C83" />
                  <templateId root="2.16.840.1.113883.10.20.1.29" assigningAuthorityName="CCD" />
                  <templateId root="1.3.6.1.4.1.19376.1.5.3.1.4.19" assigningAuthorityName="IHE PCC" />
                  <!--Result procedure observation template-->
                  <id root="903FB46B-9893-4C0F-89E0-46F06F0AACBD" />
                  <code codeSystem="2.16.840.1.113883.6.1" codeSystemName="LOINC" code="24108-3" displayName="CA 19-9">
                    <originalText>
                      <reference value="#result-7" />
                    </originalText>
                  </code>
                  <text>
                    <reference value="#result-7" />
                  </text>
                  <statusCode code="completed" />
                  <effectiveTime value="20121106200000" />
                  <performer typeCode="PRF">
                    <time>
                      <high value="20121106200000" />
                    </time>
                    <assignedEntity>
                      <id extension="703927546" root="2.16.840.1.113883.4.450" />
                      <addr use="WP">
                        <streetAddressLine>6410 North Pine Street</streetAddressLine>
                        <city>Silver Creek</city>
                        <state>NY</state>
                        <postalCode>14136</postalCode>
                      </addr>
                      <telecom value="tel:+1-619-624-5122" use="WP" />
                      <assignedPerson>
                        <realmCode code="US" />
                        <name>
                          <given>Ryan</given>
                          <family>Quinn</family>
                          <suffix></suffix>
                        </name>
                      </assignedPerson>
                      <representedOrganization>
                        <id nullFlavor="UNK" />
                        <name>Young Health Labs</name>
                        <telecom use="WP" value="tel:+1-619-624-5122" />
                        <addr use="WP">
                          <streetAddressLine>6410 North Pine Street</streetAddressLine>
                          <city>Silver Creek</city>
                          <state>NY</state>
                          <postalCode>14136</postalCode>
                        </addr>
                      </representedOrganization>
                    </assignedEntity>
                  </performer>
                </procedure>
              </component>
              <component>
                <observation classCode="OBS" moodCode="EVN">
                  <templateId root="2.16.840.1.113883.3.88.11.83.15.1" assigningAuthorityName="HITSP C83" />
                  <templateId root="2.16.840.1.113883.10.20.1.31" assigningAuthorityName="CCD" />
                  <templateId root="1.3.6.1.4.1.19376.1.5.3.1.4.13" assigningAuthorityName="IHE PCC" />
                  <!--Result observation template-->
                  <id root="1BB95185-ACF6-4A19-8A27-9DF9231A35F7" />
                  <code code="24108-3" displayName="CA 19-9" codeSystem="2.16.840.1.113883.6.1" codeSystemName="LOINC" />
                  <text>
                    <reference value="#result-7_4_1" />
                  </text>
                  <statusCode code="completed" />
                  <effectiveTime value="20121107012650" />
                  <value xsi:type="PQ" value="120" unit="U/mL" />
                </observation>
              </component>
            </organizer>
          </entry>
        </section>
      </component>
      <component>
        <!--Medications Section-->
        <section>
          <templateId root="2.16.840.1.113883.3.88.11.83.112" assigningAuthorityName="HITSP/C83" />
          <templateId root="1.3.6.1.4.1.19376.1.5.3.1.3.19" assigningAuthorityName="IHE PCC" />
          <templateId root="2.16.840.1.113883.10.20.1.8" assigningAuthorityName="HL7 CCD" />
          <code code="10160-0" displayName="History of medication use" codeSystem="2.16.840.1.113883.6.1" codeSystemName="LOINC" />
          <title>Medications</title>
          <text>
            <table border="1" width="100%">
              <thead>
                <tr>
                  <th>Medication</th>
                  <th>Dosage</th>
                  <th>Days Supplied</th>
                  <th>Last Filled Date</th>
                  <th>Refills Remaining</th>
                  <th>Status</th>
                </tr>
              </thead>
              <tbody>
                <tr>
                  <td>
                    <content ID="med-1">FLUOROURACIL</content>
                  </td>
                  <td>500 mg</td>
                  <td>32</td>
                  <td>2012-11-06T09:46:00Z</td>
                  <td>0</td>
                  <td>Active</td>
                </tr>
                <tr>
                  <td>
                    <content ID="med-2">mitomycin</content>
                  </td>
                  <td>10 mg/m2</td>
                  <td>1</td>
                  <td>2012-11-06T09:46:00Z</td>
                  <td>0</td>
                  <td>Active</td>
                </tr>
              </tbody>
            </table>
          </text>
          <entry typeCode="DRIV">
            <substanceAdministration moodCode="EVN" classCode="SBADM">
              <templateId root="2.16.840.1.113883.3.88.11.83.8" assigningAuthorityName="HITSP C83" />
              <templateId root="2.16.840.1.113883.10.20.1.24" assigningAuthorityName="CCD" />
              <templateId root="1.3.6.1.4.1.19376.1.5.3.1.4.7" assigningAuthorityName="IHE PCC" />
              <templateId root="1.3.6.1.4.1.19376.1.5.3.1.4.7.1" assigningAuthorityName="IHE PCC" />
              <id root="5E3D7BA1-FD33-43C0-8158-8797E02A8DB5" />
              <statusCode code="completed" />
              <effectiveTime xsi:type="IVL_TS">
                <low value="20121106094600" />
                <high nullFlavor="UNK" />
              </effectiveTime>
              <doseQuantity value="500" unit="mg" />
              <consumable>
                <manufacturedProduct>
                  <templateId root="2.16.840.1.113883.3.88.11.83.8.2" assigningAuthorityName="HITSP C83" />
                  <templateId root="2.16.840.1.113883.10.20.1.53" />
                  <templateId root="1.3.6.1.4.1.19376.1.5.3.1.4.7.2" assigningAuthorityName="IHE PCC" />
                  <manufacturedMaterial>
                    <code code="66758004403" displayName="FLUOROURACIL" codeSystemName="NDC" codeSystem="2.16.840.1.113883.6.69">
                      <originalText>
                        <reference value="#med-1" />
                      </originalText>
                    </code>
                    <name>FLUOROURACIL</name>
                  </manufacturedMaterial>
                </manufacturedProduct>
              </consumable>
              <entryRelationship typeCode="SUBJ">
                <observation classCode="OBS" moodCode="EVN">
                  <templateId root="2.16.840.1.113883.3.88.11.83.8.1" />
                  <code code="73639000" displayName="Prescription Drug" codeSystem="2.16.840.1.113883.6.96" codeSystemName="SNOMED CT" />
                  <statusCode code="completed" />
                </observation>
              </entryRelationship>
              <entryRelationship typeCode="REFR">
                <observation classCode="OBS" moodCode="EVN">
                  <templateId root="2.16.840.1.113883.10.20.1.57" />
                  <templateId root="2.16.840.1.113883.10.20.1.47" />
                  <code code="33999-4" codeSystem="2.16.840.1.113883.6.1" displayName="Status" codeSystemName="LOINC" />
                  <statusCode code="completed" />
                  <value xsi:type="CE" code="55561003" displayName="Active" codeSystem="2.16.840.1.113883.6.96" codeSystemName="SNOMED CT" />
                </observation>
              </entryRelationship>
              <entryRelationship typeCode="REFR">
                <supply classCode="SPLY" moodCode="INT">
                  <templateId root="2.16.840.1.113883.3.88.11.83.8.3" />
                  <templateId root="1.3.6.1.4.1.19376.1.5.3.1.4.7.3" />
                  <templateId root="2.16.840.1.113883.10.20.1.34" />
                  <id root="2.16.840.1.113883.4.450" extension="121031-09706" />
                  <repeatNumber value="1" />
                  <quantity value="14880" unit="{UNASSIGNED}" />
                  <author>
                    <time value="20121031131500" />
                    <assignedAuthor>
                      <id extension="939119500" root="2.16.840.1.113883.4.450" />
                      <addr use="WP">
                        <streetAddressLine>6321 Lacey Drive</streetAddressLine>
                        <city>Lakewood</city>
                        <state>NY</state>
                        <postalCode>14750</postalCode>
                      </addr>
                      <telecom value="tel:+1-504-692-1745" use="WP" />
                      <assignedPerson>
                        <realmCode code="US" />
                        <name>
                          <given>Gisela</given>
                          <family>Griffin</family>
                          <suffix>Dr.</suffix>
                        </name>
                      </assignedPerson>
                      <representedOrganization>
                        <id nullFlavor="UNK" />
                        <name>Joel Wilkerson MD</name>
                        <telecom use="WP" value="tel:+1-504-692-1745" />
                        <addr use="WP">
                          <streetAddressLine>6321 Lacey Drive</streetAddressLine>
                          <city>Lakewood</city>
                          <state>NY</state>
                          <postalCode>14750</postalCode>
                        </addr>
                      </representedOrganization>
                    </assignedAuthor>
                  </author>
                </supply>
              </entryRelationship>
              <entryRelationship typeCode="REFR">
                <supply classCode="SPLY" moodCode="EVN">
                  <templateId root="2.16.840.1.113883.10.20.1.34" assigningAuthorityName="CCD" />
                  <id root="2.16.840.1.113883.4.450" extension="RX81150349" assigningAuthorityName="Metro Drugs" />
                  <code nullFlavor="NA" />
                  <statusCode code="completed" />
                  <effectiveTime value="20121106094600" />
                  <repeatNumber value="1" />
                  <quantity value="14880" />
                  <performer>
                    <assignedEntity>
                      <id extension="213830980" root="2.16.840.1.113883.4.450" />
                      <addr use="WP">
                        <streetAddressLine>5097 Old Seward Highway</streetAddressLine>
                        <city>Westfield</city>
                        <state>NY</state>
                        <postalCode>14787</postalCode>
                      </addr>
                      <telecom value="tel:+1-212-787-9327" use="WP" />
                      <assignedPerson>
                        <realmCode code="US" />
                        <name>
                          <given>Anika</given>
                          <family>Boyd</family>
                          <suffix></suffix>
                        </name>
                      </assignedPerson>
                      <representedOrganization>
                        <id nullFlavor="UNK" />
                        <name>Metro Drugs</name>
                        <telecom use="WP" value="tel:+1-212-787-9327" />
                        <addr use="WP">
                          <streetAddressLine>5097 Old Seward Highway</streetAddressLine>
                          <city>Westfield</city>
                          <state>NY</state>
                          <postalCode>14787</postalCode>
                        </addr>
                      </representedOrganization>
                    </assignedEntity>
                  </performer>
                </supply>
              </entryRelationship>
            </substanceAdministration>
          </entry>
          <entry typeCode="DRIV">
            <substanceAdministration moodCode="EVN" classCode="SBADM">
              <templateId root="2.16.840.1.113883.3.88.11.83.8" assigningAuthorityName="HITSP C83" />
              <templateId root="2.16.840.1.113883.10.20.1.24" assigningAuthorityName="CCD" />
              <templateId root="1.3.6.1.4.1.19376.1.5.3.1.4.7" assigningAuthorityName="IHE PCC" />
              <templateId root="1.3.6.1.4.1.19376.1.5.3.1.4.7.1" assigningAuthorityName="IHE PCC" />
              <id root="CBCBB845-EF8B-4134-816B-1DEAA4A6A28D" />
              <statusCode code="completed" />
              <effectiveTime xsi:type="IVL_TS">
                <low value="20121106094600" />
                <high nullFlavor="UNK" />
              </effectiveTime>
              <doseQuantity value="10" unit="mg/m2" />
              <consumable>
                <manufacturedProduct>
                  <templateId root="2.16.840.1.113883.3.88.11.83.8.2" assigningAuthorityName="HITSP C83" />
                  <templateId root="2.16.840.1.113883.10.20.1.53" />
                  <templateId root="1.3.6.1.4.1.19376.1.5.3.1.4.7.2" assigningAuthorityName="IHE PCC" />
                  <manufacturedMaterial>
                    <code code="16729-*108-11" displayName="mitomycin" codeSystemName="NDC" codeSystem="2.16.840.1.113883.6.69">
                      <originalText>
                        <reference value="#med-2" />
                      </originalText>
                    </code>
                    <name>mitomycin</name>
                  </manufacturedMaterial>
                </manufacturedProduct>
              </consumable>
              <entryRelationship typeCode="SUBJ">
                <observation classCode="OBS" moodCode="EVN">
                  <templateId root="2.16.840.1.113883.3.88.11.83.8.1" />
                  <code code="73639000" displayName="Prescription Drug" codeSystem="2.16.840.1.113883.6.96" codeSystemName="SNOMED CT" />
                  <statusCode code="completed" />
                </observation>
              </entryRelationship>
              <entryRelationship typeCode="REFR">
                <observation classCode="OBS" moodCode="EVN">
                  <templateId root="2.16.840.1.113883.10.20.1.57" />
                  <templateId root="2.16.840.1.113883.10.20.1.47" />
                  <code code="33999-4" codeSystem="2.16.840.1.113883.6.1" displayName="Status" codeSystemName="LOINC" />
                  <statusCode code="completed" />
                  <value xsi:type="CE" code="55561003" displayName="Active" codeSystem="2.16.840.1.113883.6.96" codeSystemName="SNOMED CT" />
                </observation>
              </entryRelationship>
              <entryRelationship typeCode="REFR">
                <supply classCode="SPLY" moodCode="INT">
                  <templateId root="2.16.840.1.113883.3.88.11.83.8.3" />
                  <templateId root="1.3.6.1.4.1.19376.1.5.3.1.4.7.3" />
                  <templateId root="2.16.840.1.113883.10.20.1.34" />
                  <id root="2.16.840.1.113883.4.450" extension="121031-53804" />
                  <repeatNumber value="1" />
                  <quantity value="18.6" unit="{UNASSIGNED}" />
                  <author>
                    <time value="20121031131500" />
                    <assignedAuthor>
                      <id extension="939119500" root="2.16.840.1.113883.4.450" />
                      <addr use="WP">
                        <streetAddressLine>6321 Lacey Drive</streetAddressLine>
                        <city>Lakewood</city>
                        <state>NY</state>
                        <postalCode>14750</postalCode>
                      </addr>
                      <telecom value="tel:+1-504-692-1745" use="WP" />
                      <assignedPerson>
                        <realmCode code="US" />
                        <name>
                          <given>Gisela</given>
                          <family>Griffin</family>
                          <suffix>Dr.</suffix>
                        </name>
                      </assignedPerson>
                      <representedOrganization>
                        <id nullFlavor="UNK" />
                        <name>Joel Wilkerson MD</name>
                        <telecom use="WP" value="tel:+1-504-692-1745" />
                        <addr use="WP">
                          <streetAddressLine>6321 Lacey Drive</streetAddressLine>
                          <city>Lakewood</city>
                          <state>NY</state>
                          <postalCode>14750</postalCode>
                        </addr>
                      </representedOrganization>
                    </assignedAuthor>
                  </author>
                </supply>
              </entryRelationship>
              <entryRelationship typeCode="REFR">
                <supply classCode="SPLY" moodCode="EVN">
                  <templateId root="2.16.840.1.113883.10.20.1.34" assigningAuthorityName="CCD" />
                  <id root="2.16.840.1.113883.4.450" extension="RX75780546" assigningAuthorityName="Metro Drugs" />
                  <code nullFlavor="NA" />
                  <statusCode code="completed" />
                  <effectiveTime value="20121106094600" />
                  <repeatNumber value="1" />
                  <quantity value="18.6" />
                  <performer>
                    <assignedEntity>
                      <id extension="213830980" root="2.16.840.1.113883.4.450" />
                      <addr use="WP">
                        <streetAddressLine>5097 Old Seward Highway</streetAddressLine>
                        <city>Westfield</city>
                        <state>NY</state>
                        <postalCode>14787</postalCode>
                      </addr>
                      <telecom value="tel:+1-212-787-9327" use="WP" />
                      <assignedPerson>
                        <realmCode code="US" />
                        <name>
                          <given>Anika</given>
                          <family>Boyd</family>
                          <suffix></suffix>
                        </name>
                      </assignedPerson>
                      <representedOrganization>
                        <id nullFlavor="UNK" />
                        <name>Metro Drugs</name>
                        <telecom use="WP" value="tel:+1-212-787-9327" />
                        <addr use="WP">
                          <streetAddressLine>5097 Old Seward Highway</streetAddressLine>
                          <city>Westfield</city>
                          <state>NY</state>
                          <postalCode>14787</postalCode>
                        </addr>
                      </representedOrganization>
                    </assignedEntity>
                  </performer>
                </supply>
              </entryRelationship>
            </substanceAdministration>
          </entry>
        </section>
      </component>
      <component>
        <!--Vital signs Section-->
        <section>
          <templateId root="2.16.840.1.113883.10.20.1.16" assigningAuthorityName="HL7 CCD" />
          <templateId root="2.16.840.1.113883.3.88.11.83.119" assigningAuthorityName="HITSP/C83" />
          <templateId root="1.3.6.1.4.1.19376.1.5.3.1.1.5.3.2" assigningAuthorityName="IHE PCC" />
          <templateId root="1.3.6.1.4.1.19376.1.5.3.1.3.25" assigningAuthorityName="IHE PCC" />
          <!--Vital Signs section template-->
          <code code="8716-3" codeSystem="2.16.840.1.113883.6.1" codeSystemName="LOINC" displayName="Vital signs" />
          <title>Vital Signs</title>
          <text>
            <table border="1" width="100%">
              <thead>
                <tr>
                  <th>Date</th>
                  <th>Body height</th>
                  <th>Body weight</th>
                  <th>Respiration Rate</th>
                  <th>Pulse</th>
                  <th>Systolic BP</th>
                  <th>Diastolic BP</th>
                  <th>Temperature</th>
                </tr>
              </thead>
              <tbody>
                <tr>
                  <td>2012-10-31T13:15:00Z</td>
                  <td>
                    <content ID="vital_1">166 cm</content>
                  </td>
                  <td>
                    <content ID="vital_2">43.5 kg</content>
                  </td>
                  <td>
                    <content ID="vital_3">15 /min</content>
                  </td>
                  <td>
                    <content ID="vital_4">74 /min</content>
                  </td>
                  <td>
                    <content ID="vital_5">104 mm[Hg]</content>
                  </td>
                  <td>
                    <content ID="vital_6">63 mm[Hg]</content>
                  </td>
                  <td>
                    <content ID="vital_7">36.6 Cel</content>
                  </td>
                </tr>
              </tbody>
            </table>
          </text>
          <entry typeCode="DRIV">
            <organizer classCode="CLUSTER" moodCode="EVN">
              <templateId root="2.16.840.1.113883.10.20.1.32" assigningAuthorityName="CCD" />
              <templateId root="2.16.840.1.113883.10.20.1.35" assigningAuthorityName="CCD" />
              <templateId root="1.3.6.1.4.1.19376.1.5.3.1.4.13.1" assigningAuthorityName="IHE PCC" />
              <!--Vital signs organizer template-->
              <id root="2CE6532D-A45C-4E87-8084-221F781A8E6D" />
              <code code="46680005" codeSystem="2.16.840.1.113883.6.96" displayName="Vital signs" codeSystemName="SNOMED CT" />
              <statusCode code="completed" />
              <effectiveTime value="20121031131500" />
              <component>
                <observation classCode="OBS" moodCode="EVN">
                  <templateId root="1.3.6.1.4.1.19376.1.5.3.1.4.13.2" assigningAuthorityName="IHE PCC" />
                  <templateId root="1.3.6.1.4.1.19376.1.5.3.1.4.13" assigningAuthorityName="IHE PCC" />
                  <templateId root="2.16.840.1.113883.10.20.1.31" assigningAuthorityName="CCD" />
                  <templateId root="2.16.840.1.113883.3.88.11.83.14" assigningAuthorityName="HITSP/C83" />
                  <!--Result observation template-->
                  <id root="DCC77027-4949-40F8-8938-E7CA8DFE9AA4" />
                  <code code="8302-2" codeSystem="2.16.840.1.113883.6.1" codeSystemName="LOINC" displayName="Body height" />
                  <text>
                    <reference value="#vital_1" />
                  </text>
                  <statusCode code="completed" />
                  <effectiveTime value="20121031131500" />
                  <value xsi:type="PQ" value="166" unit="cm" />
                </observation>
              </component>
              <component>
                <observation classCode="OBS" moodCode="EVN">
                  <templateId root="1.3.6.1.4.1.19376.1.5.3.1.4.13.2" assigningAuthorityName="IHE PCC" />
                  <templateId root="1.3.6.1.4.1.19376.1.5.3.1.4.13" assigningAuthorityName="IHE PCC" />
                  <templateId root="2.16.840.1.113883.10.20.1.31" assigningAuthorityName="CCD" />
                  <templateId root="2.16.840.1.113883.3.88.11.83.14" assigningAuthorityName="HITSP/C83" />
                  <!--Result observation template-->
                  <id root="6DC5D7CE-799C-4219-88E5-FF2A73EC195A" />
                  <code code="3141-9" codeSystem="2.16.840.1.113883.6.1" codeSystemName="LOINC" displayName="Body weight" />
                  <text>
                    <reference value="#vital_2" />
                  </text>
                  <statusCode code="completed" />
                  <effectiveTime value="20121031131500" />
                  <value xsi:type="PQ" value="43.5" unit="kg" />
                </observation>
              </component>
              <component>
                <observation classCode="OBS" moodCode="EVN">
                  <templateId root="1.3.6.1.4.1.19376.1.5.3.1.4.13.2" assigningAuthorityName="IHE PCC" />
                  <templateId root="1.3.6.1.4.1.19376.1.5.3.1.4.13" assigningAuthorityName="IHE PCC" />
                  <templateId root="2.16.840.1.113883.10.20.1.31" assigningAuthorityName="CCD" />
                  <templateId root="2.16.840.1.113883.3.88.11.83.14" assigningAuthorityName="HITSP/C83" />
                  <!--Result observation template-->
                  <id root="68007D0E-546F-4C6A-823C-5A4907FF7AEF" />
                  <code code="9279-1" codeSystem="2.16.840.1.113883.6.1" codeSystemName="LOINC" displayName="RESPIRATION RATE" />
                  <text>
                    <reference value="#vital_3" />
                  </text>
                  <statusCode code="completed" />
                  <effectiveTime value="20121031131500" />
                  <value xsi:type="PQ" value="15" unit="/min" />
                </observation>
              </component>
              <component>
                <observation classCode="OBS" moodCode="EVN">
                  <templateId root="1.3.6.1.4.1.19376.1.5.3.1.4.13.2" assigningAuthorityName="IHE PCC" />
                  <templateId root="1.3.6.1.4.1.19376.1.5.3.1.4.13" assigningAuthorityName="IHE PCC" />
                  <templateId root="2.16.840.1.113883.10.20.1.31" assigningAuthorityName="CCD" />
                  <templateId root="2.16.840.1.113883.3.88.11.83.14" assigningAuthorityName="HITSP/C83" />
                  <!--Result observation template-->
                  <id root="848EFE23-1BAA-4254-82FC-8B04B4D32EA9" />
                  <code code="8867-4" codeSystem="2.16.840.1.113883.6.1" codeSystemName="LOINC" displayName="HEART BEAT" />
                  <text>
                    <reference value="#vital_4" />
                  </text>
                  <statusCode code="completed" />
                  <effectiveTime value="20121031131500" />
                  <value xsi:type="PQ" value="74" unit="/min" />
                </observation>
              </component>
              <component>
                <observation classCode="OBS" moodCode="EVN">
                  <templateId root="1.3.6.1.4.1.19376.1.5.3.1.4.13.2" assigningAuthorityName="IHE PCC" />
                  <templateId root="1.3.6.1.4.1.19376.1.5.3.1.4.13" assigningAuthorityName="IHE PCC" />
                  <templateId root="2.16.840.1.113883.10.20.1.31" assigningAuthorityName="CCD" />
                  <templateId root="2.16.840.1.113883.3.88.11.83.14" assigningAuthorityName="HITSP/C83" />
                  <!--Result observation template-->
                  <id root="925CB510-CC73-4A50-8519-D97A840F55E3" />
                  <code code="8480-6" codeSystem="2.16.840.1.113883.6.1" codeSystemName="LOINC" displayName="Systolic BP" />
                  <text>
                    <reference value="#vital_5" />
                  </text>
                  <statusCode code="completed" />
                  <effectiveTime value="20121031131500" />
                  <value xsi:type="PQ" value="104" unit="mm[Hg]" />
                </observation>
              </component>
              <component>
                <observation classCode="OBS" moodCode="EVN">
                  <templateId root="1.3.6.1.4.1.19376.1.5.3.1.4.13.2" assigningAuthorityName="IHE PCC" />
                  <templateId root="1.3.6.1.4.1.19376.1.5.3.1.4.13" assigningAuthorityName="IHE PCC" />
                  <templateId root="2.16.840.1.113883.10.20.1.31" assigningAuthorityName="CCD" />
                  <templateId root="2.16.840.1.113883.3.88.11.83.14" assigningAuthorityName="HITSP/C83" />
                  <!--Result observation template-->
                  <id root="4B26CD6C-AC47-4ECB-884B-5F00793A6958" />
                  <code code="8462-4" codeSystem="2.16.840.1.113883.6.1" codeSystemName="LOINC" displayName="Diastolic BP" />
                  <text>
                    <reference value="#vital_6" />
                  </text>
                  <statusCode code="completed" />
                  <effectiveTime value="20121031131500" />
                  <value xsi:type="PQ" value="63" unit="mm[Hg]" />
                </observation>
              </component>
              <component>
                <observation classCode="OBS" moodCode="EVN">
                  <templateId root="1.3.6.1.4.1.19376.1.5.3.1.4.13.2" assigningAuthorityName="IHE PCC" />
                  <templateId root="1.3.6.1.4.1.19376.1.5.3.1.4.13" assigningAuthorityName="IHE PCC" />
                  <templateId root="2.16.840.1.113883.10.20.1.31" assigningAuthorityName="CCD" />
                  <templateId root="2.16.840.1.113883.3.88.11.83.14" assigningAuthorityName="HITSP/C83" />
                  <!--Result observation template-->
                  <id root="E93BE00F-DDB9-4A16-8DEC-9CEB001FA2C1" />
                  <code code="8310-5" codeSystem="2.16.840.1.113883.6.1" codeSystemName="LOINC" displayName="BODY TEMPERATURE" />
                  <text>
                    <reference value="#vital_7" />
                  </text>
                  <statusCode code="completed" />
                  <effectiveTime value="20121031131500" />
                  <value xsi:type="PQ" value="36.6" unit="Cel" />
                </observation>
              </component>
            </organizer>
          </entry>
        </section>
      </component>
      <component>
        <!--Encounters Section-->
        <section>
          <templateId root="2.16.840.1.113883.3.88.11.83.127" assigningAuthorityName="HITSP C83" />
          <templateId root="1.3.6.1.4.1.19376.1.5.3.1.1.5.3.3" assigningAuthorityName="IHE PCC" />
          <templateId root="2.16.840.1.113883.10.20.1.3" assigningAuthorityName="HL7 CCD" />
          <!--Encounters section template-->
          <code code="46240-8" codeSystem="2.16.840.1.113883.6.1" codeSystemName="LOINC" displayName="History of encounters" />
          <title>Encounters</title>
          <text>
            <table border="1" width="100%">
              <thead>
                <tr>
                  <th>Date</th>
                  <th>Encounter</th>
                  <th>Performer</th>
                  <th>Location</th>
                  <th>Notes</th>
                </tr>
              </thead>
              <tbody>
                <tr>
                  <td>2012-10-31T13:15:00Z</td>
                  <td>
                    <content ID="encounter-1">Walk-In</content>
                  </td>
                  <td>Gisela Griffin MD</td>
                  <td>Joel Wilkerson MD</td>
                  <td>
                    <content ID="encounter-note-1">s:patient presents with mild vomiting, severe pain all over the abdomen. pt also reports of mild recurrent epigastric pain. patient is a 49 yo F. o:Height 166 cm, Weight 43.5 kg, Temperature 36.6 C, Pulse 74, SystolicBP 104, DiastolicBP 63, Respiration 15 a:Pancreatic Cancer p:performed E/M Level 2 (new patient) - Completed, and prescribed FLUOROURACIL - 500 mg IV, mitomycin - 10 mg/m2 IV, and ordered Comprehensive Metabolic Panel, Amylase, Lipase, CA 19-9.</content>
                    <content2 ID="encounter-note-1" xmlns="">
                      <Term Catalog="SYM_CA_SOAP_HEADERS" SOAP_SECTION="Subjective" Code="15">s:</Term>
                      <Unmatched>patient presents</Unmatched>
                      <Unmatched>with</Unmatched>
                      <Term Catalog="SNOMED_CT_QUALIFIERS_US" QUALIFIER="Mild (qualifier value)" Code="255604002">Mild</Term>
                      <Term Catalog="SYM_SNO_INT_USEXT" DISEASE="Vomiting" Code="422400008">Vomiting</Term>
                      <Unmatched>,</Unmatched>
                      <Term Catalog="SYM_SNO_INT_USEXT" SYMPTOM="Severe pain" Code="76948002">Severe pain</Term>
                      <Unmatched>all over</Unmatched>
                      <Unmatched>the</Unmatched>
                      <Unmatched>abdomen</Unmatched>
                      <Unmatched>pt also reports</Unmatched>
                      <Unmatched>of</Unmatched>
                      <Unmatched>mild recurrent</Unmatched>
                      <Term Catalog="SYM_SNO_INT_USEXT" SYMPTOM="Epigastric pain" Code="79922009">Epigastric pain</Term>
                      <Unmatched>patient is a</Unmatched>
                      <SiftGroup>
                        <Value Value="49">49</Value>
                        <Term Catalog="SYM_CA_SIFT_TIME_UNIT" AGE_UNIT_OF_MEASURE="year" Code="14">yo</Term>
                      </SiftGroup>
                      <Term Catalog="SYM_CA_SIFT_GENDER" GENDER="Female" Code="F">F</Term>
                      <Term Catalog="SYM_CA_SOAP_HEADERS" SOAP_SECTION="Objective" Code="11">o:</Term>
                      <SiftGroup>
                        <Term Catalog="SYM_CA_VITALS" VITAL_SIGN="height" Code="2">height</Term>
                        <Value Value="166">166</Value>
                        <Term Catalog="SYM_CA_UOM" VITAL_SIGN_UOM="centimeter" Code="16">cm</Term>
                      </SiftGroup>
                      <Unmatched>,</Unmatched>
                      <SiftGroup>
                        <Term Catalog="SYM_CA_VITALS" VITAL_SIGN="weight" Code="7">weight</Term>
                        <Value Value="43.5">43.5</Value>
                        <Term Catalog="SYM_CA_UOM" VITAL_SIGN_UOM="kilogram" Code="3">kg</Term>
                      </SiftGroup>
                      <Unmatched>,</Unmatched>
                      <SiftGroup>
                        <Term Catalog="SYM_CA_VITALS" VITAL_SIGN="temperature" Code="6">temperature</Term>
                        <Value Value="36.6">36.6</Value>
                        <Term Catalog="SYM_CA_UOM" VITAL_SIGN_UOM="degree, Celsius" Code="42">C</Term>
                      </SiftGroup>
                      <Unmatched>,</Unmatched>
                      <SiftGroup>
                        <Term Catalog="SYM_CA_VITALS" VITAL_SIGN="pulse" Code="3">pulse</Term>
                        <Value Value="74">74</Value>
                      </SiftGroup>
                      <Unmatched>,</Unmatched>
                      <SiftGroup>
                        <Term Catalog="SYM_CA_VITALS" VITAL_SIGN="systolic blood pressure" Code="5">systolicbp</Term>
                        <Value Value="104">104</Value>
                      </SiftGroup>
                      <Unmatched>,</Unmatched>
                      <SiftGroup>
                        <Term Catalog="SYM_CA_VITALS" VITAL_SIGN="diastolic blood pressure" Code="1">diastolicbp</Term>
                        <Value Value="63">63</Value>
                      </SiftGroup>
                      <Unmatched>,</Unmatched>
                      <SiftGroup>
                        <Term Catalog="SYM_CA_VITALS" VITAL_SIGN="respiration" Code="4">respiration</Term>
                        <Value Value="15">15</Value>
                      </SiftGroup>
                      <Term Catalog="SYM_CA_SOAP_HEADERS" SOAP_SECTION="Assessment" Code="2">a:</Term>
                      <Unmatched>Pancreatic Cancer</Unmatched>
                      <Term Catalog="SYM_CA_SOAP_HEADERS" SOAP_SECTION="Plan" Code="12">p:</Term>
                      <Unmatched>performed</Unmatched>
                      <Value Value="E/MALE Level 2 (new patient) - Completed , ">E/MALE Level 2 (new patient) - Completed , </Value>
                      <Unmatched>and</Unmatched>
                      <Unmatched>prescribed</Unmatched>
                      <Term Catalog="SYM_NLM_RXNFULL" DRUG="Fluorouracil" Code="4492">Fluorouracil</Term>
                      <Unmatched>-</Unmatched>
                      <Unmatched>500</Unmatched>
                      <Unmatched>mg IV ,</Unmatched>
                      <Term Catalog="SYM_NLM_RXNFULL" DRUG="Mitomycin" Code="632">Mitomycin</Term>
                      <Unmatched>-</Unmatched>
                      <Unmatched>10</Unmatched>
                      <Unmatched>mg/m</Unmatched>
                      <Unmatched>2</Unmatched>
                      <Unmatched>IV ,</Unmatched>
                      <Unmatched>and</Unmatched>
                      <Value Value="ordered Comprehensive Metabolic Panel , Amylase , Lipase , CA 19 - 9">ordered Comprehensive Metabolic Panel , Amylase , Lipase , CA 19 - 9</Value>
                    </content2>
                  </td>
                </tr>
                <tr>
                  <td>2012-11-06T20:00:00Z</td>
                  <td>
                    <content ID="encounter-2">Walk-In</content>
                  </td>
                  <td>Ryan Quinn </td>
                  <td>Young Health Labs</td>
                  <td>
                    <content ID="encounter-note-2"></content>
                    <content2 ID="encounter-note-2" xmlns=""></content2>
                  </td>
                </tr>
              </tbody>
            </table>
          </text>
          <entry typeCode="DRIV">
            <encounter classCode="ENC" moodCode="EVN">
              <templateId root="2.16.840.1.113883.3.88.11.83.16" assigningAuthorityName="HITSP/C83" />
              <templateId root="1.3.6.1.4.1.19376.1.5.3.1.4.14" assigningAuthorityName="IHE PCC" />
              <templateId root="2.16.840.1.113883.10.20.1.21" assigningAuthorityName="HITSP/C83" />
              <!--Encounter activity template-->
              <id root="2.16.840.1.113883.4.450" extension="80488612024470943899" />
              <code code="99202" displayName="E/M Level 2 (new patient)" codeSystemName="CPT" codeSystemVersion="4" codeSystem="2.16.840.1.113883.6.12">
                <originalText>
                  <reference value="#encounter-1" />
                </originalText>
                <translation code="AMB" displayName="Ambulatory" codeSystemName="ActEncounterCode" codeSystem="2.16.840.1.113883.5.4" />
              </code>
              <text>
                <reference value="#encounter-note-1" />
              </text>
              <effectiveTime>
                <low value="20121031131500" />
                <high value="20121031131500" />
              </effectiveTime>
              <performer typeCode="PRF">
                <time>
                  <high value="20121031131500" />
                </time>
                <assignedEntity>
                  <id extension="939119500" root="2.16.840.1.113883.4.450" />
                  <addr use="WP">
                    <streetAddressLine>6321 Lacey Drive</streetAddressLine>
                    <city>Lakewood</city>
                    <state>NY</state>
                    <postalCode>14750</postalCode>
                  </addr>
                  <telecom value="tel:+1-504-692-1745" use="WP" />
                  <assignedPerson>
                    <realmCode code="US" />
                    <name>
                      <given>Gisela</given>
                      <family>Griffin</family>
                      <suffix>MD</suffix>
                    </name>
                  </assignedPerson>
                  <representedOrganization>
                    <id nullFlavor="UNK" />
                    <name>Joel Wilkerson MD</name>
                    <telecom use="WP" value="tel:+1-504-692-1745" />
                    <addr use="WP">
                      <streetAddressLine>6321 Lacey Drive</streetAddressLine>
                      <city>Lakewood</city>
                      <state>NY</state>
                      <postalCode>14750</postalCode>
                    </addr>
                  </representedOrganization>
                </assignedEntity>
              </performer>
              <participant typeCode="LOC">
                <participantRole classCode="SDLOC">
                  <addr use="WP">
                    <streetAddressLine>6321 Lacey Drive</streetAddressLine>
                    <city>Lakewood</city>
                    <state>NY</state>
                    <postalCode>14750</postalCode>
                  </addr>
                  <telecom value="tel:+1-504-692-1745" use="WP" />
                  <playingEntity>
                    <name>Joel Wilkerson MD</name>
                  </playingEntity>
                </participantRole>
              </participant>
            </encounter>
          </entry>
          <entry typeCode="DRIV">
            <encounter classCode="ENC" moodCode="EVN">
              <templateId root="2.16.840.1.113883.3.88.11.83.16" assigningAuthorityName="HITSP/C83" />
              <templateId root="1.3.6.1.4.1.19376.1.5.3.1.4.14" assigningAuthorityName="IHE PCC" />
              <templateId root="2.16.840.1.113883.10.20.1.21" assigningAuthorityName="HITSP/C83" />
              <!--Encounter activity template-->
              <id root="2.16.840.1.113883.4.450" extension="70511931916233146884" />
              <code code="AMB" displayName="Ambulatory" codeSystemName="ActEncounterCode" codeSystem="2.16.840.1.113883.5.4">
                <originalText>
                  <reference value="#encounter-2" />
                </originalText>
              </code>
              <text>
                <reference value="#encounter-note-2" />
              </text>
              <effectiveTime>
                <low value="20121106200000" />
                <high value="20121106200000" />
              </effectiveTime>
              <performer typeCode="PRF">
                <time>
                  <high value="20121106200000" />
                </time>
                <assignedEntity>
                  <id extension="703927546" root="2.16.840.1.113883.4.450" />
                  <addr use="WP">
                    <streetAddressLine>6410 North Pine Street</streetAddressLine>
                    <city>Silver Creek</city>
                    <state>NY</state>
                    <postalCode>14136</postalCode>
                  </addr>
                  <telecom value="tel:+1-619-624-5122" use="WP" />
                  <assignedPerson>
                    <realmCode code="US" />
                    <name>
                      <given>Ryan</given>
                      <family>Quinn</family>
                      <suffix></suffix>
                    </name>
                  </assignedPerson>
                  <representedOrganization>
                    <id nullFlavor="UNK" />
                    <name>Young Health Labs</name>
                    <telecom use="WP" value="tel:+1-619-624-5122" />
                    <addr use="WP">
                      <streetAddressLine>6410 North Pine Street</streetAddressLine>
                      <city>Silver Creek</city>
                      <state>NY</state>
                      <postalCode>14136</postalCode>
                    </addr>
                  </representedOrganization>
                </assignedEntity>
              </performer>
              <participant typeCode="LOC">
                <participantRole classCode="SDLOC">
                  <addr use="WP">
                    <streetAddressLine>6410 North Pine Street</streetAddressLine>
                    <city>Silver Creek</city>
                    <state>NY</state>
                    <postalCode>14136</postalCode>
                  </addr>
                  <telecom value="tel:+1-619-624-5122" use="WP" />
                  <playingEntity>
                    <name>Young Health Labs</name>
                  </playingEntity>
                </participantRole>
              </participant>
            </encounter>
          </entry>
        </section>
      </component>
      <component>
        <!--Plan of Care-->
        <section>
          <templateId root="2.16.840.1.113883.3.88.11.83.124" assigningAuthorityName="HITSP/C83" />
          <templateId root="1.3.6.1.4.1.19376.1.5.3.1.3.31" assigningAuthorityName="IHE PCC" />
          <templateId root="2.16.840.1.113883.10.20.2.7" assigningAuthorityName="HL7 CCD" />
          <templateId root="2.16.840.1.113883.10.20.1.10" assigningAuthorityName="HL7 CCD" />
          <!--Plan of Care section template-->
          <code code="18776-5" codeSystem="2.16.840.1.113883.6.1" codeSystemName="LOINC" displayName="Treatment plan" />
          <title>Plan of Care</title>
          <text>
            <table border="1" width="100%">
              <thead>
                <tr>
                  <th>Planned Activity</th>
                  <th>Planned Date</th>
                </tr>
              </thead>
              <tbody>
                <tr>
                  <td>
                    <content ID="plannedlab-1">Comprehensive Metabolic Panel</content>
                  </td>
                  <td>2012-10-31T13:15:00Z</td>
                </tr>
                <tr>
                  <td>
                    <content ID="plannedlab-2">Amylase</content>
                  </td>
                  <td>2012-10-31T13:15:00Z</td>
                </tr>
                <tr>
                  <td>
                    <content ID="plannedlab-3">Lipase</content>
                  </td>
                  <td>2012-10-31T13:15:00Z</td>
                </tr>
                <tr>
                  <td>
                    <content ID="plannedlab-4">CA 19-9</content>
                  </td>
                  <td>2012-10-31T13:15:00Z</td>
                </tr>
                <tr>
                  <td>
                    <content ID="planneddrug-1">FLUOROURACIL - 500 mg</content>
                  </td>
                  <td>2012-10-31T13:15:00Z</td>
                </tr>
                <tr>
                  <td>
                    <content ID="planneddrug-2">mitomycin - 10 mg/m2</content>
                  </td>
                  <td>2012-10-31T13:15:00Z</td>
                </tr>
              </tbody>
            </table>
          </text>
          <entry typeCode="DRIV">
            <procedure classCode="OBS" moodCode="RQO">
              <templateId root="2.16.840.1.113883.10.20.1.25" assigningAuthorityName="CCD" />
              <!--Plan of Activity activity template-->
              <id root="70814DC2-EE62-4EAA-8BD0-C1DC7FBAD962" />
              <code code="24323-8" displayName="Comprehensive Metabolic Panel" codeSystem="2.16.840.1.113883.6.103">
                <originalText>
                  <reference value="#plannedlab-1" />
                </originalText>
              </code>
              <statusCode code="new" />
              <effectiveTime>
                <center value="20121031131500" />
              </effectiveTime>
            </procedure>
          </entry>
          <entry typeCode="DRIV">
            <procedure classCode="OBS" moodCode="RQO">
              <templateId root="2.16.840.1.113883.10.20.1.25" assigningAuthorityName="CCD" />
              <!--Plan of Activity activity template-->
              <id root="D829DD81-91E8-4055-81E1-F67DA9C4A751" />
              <code code="1798-8" displayName="Amylase" codeSystem="2.16.840.1.113883.6.103">
                <originalText>
                  <reference value="#plannedlab-2" />
                </originalText>
              </code>
              <statusCode code="new" />
              <effectiveTime>
                <center value="20121031131500" />
              </effectiveTime>
            </procedure>
          </entry>
          <entry typeCode="DRIV">
            <procedure classCode="OBS" moodCode="RQO">
              <templateId root="2.16.840.1.113883.10.20.1.25" assigningAuthorityName="CCD" />
              <!--Plan of Activity activity template-->
              <id root="AA70C780-2EDA-4168-81BC-05258146BC7A" />
              <code code="3040-3" displayName="Lipase" codeSystem="2.16.840.1.113883.6.103">
                <originalText>
                  <reference value="#plannedlab-3" />
                </originalText>
              </code>
              <statusCode code="new" />
              <effectiveTime>
                <center value="20121031131500" />
              </effectiveTime>
            </procedure>
          </entry>
          <entry typeCode="DRIV">
            <procedure classCode="OBS" moodCode="RQO">
              <templateId root="2.16.840.1.113883.10.20.1.25" assigningAuthorityName="CCD" />
              <!--Plan of Activity activity template-->
              <id root="2C4F77D9-C564-4A1C-8B97-7ED2A744CA98" />
              <code code="24108-3" displayName="CA 19-9" codeSystem="2.16.840.1.113883.6.103">
                <originalText>
                  <reference value="#plannedlab-4" />
                </originalText>
              </code>
              <statusCode code="new" />
              <effectiveTime>
                <center value="20121031131500" />
              </effectiveTime>
            </procedure>
          </entry>
          <entry>
            <substanceAdministration moodCode="INT" classCode="SBADM">
              <templateId root="2.16.840.1.113883.3.88.11.83.8" assigningAuthorityName="HITSP C83" />
              <templateId root="2.16.840.1.113883.10.20.1.24" assigningAuthorityName="CCD" />
              <templateId root="1.3.6.1.4.1.19376.1.5.3.1.4.7" assigningAuthorityName="IHE PCC" />
              <templateId root="1.3.6.1.4.1.19376.1.5.3.1.4.7.1" assigningAuthorityName="IHE PCC" />
              <templateId root="2.16.840.1.113883.10.20.1.25" assigningAuthorityName="CCD" />
              <id root="2CE07772-DFE7-4D22-820C-124263AB9B82" />
              <statusCode code="completed" />
              <effectiveTime xsi:type="IVL_TS">
                <low value="20121031131500" />
                <high nullFlavor="UNK" />
              </effectiveTime>
              <doseQuantity value="500" unit="mg" />
              <consumable>
                <manufacturedProduct>
                  <templateId root="2.16.840.1.113883.3.88.11.83.8.2" assigningAuthorityName="HITSP C83" />
                  <templateId root="2.16.840.1.113883.10.20.1.53" />
                  <templateId root="1.3.6.1.4.1.19376.1.5.3.1.4.7.2" assigningAuthorityName="IHE PCC" />
                  <manufacturedMaterial>
                    <code code="66758004403" displayName="FLUOROURACIL" codeSystemName="NDC" codeSystem="2.16.840.1.113883.6.69">
                      <originalText>
                        <reference value="#med-1" />
                      </originalText>
                    </code>
                    <name>FLUOROURACIL</name>
                  </manufacturedMaterial>
                </manufacturedProduct>
              </consumable>
              <entryRelationship typeCode="SUBJ">
                <observation classCode="OBS" moodCode="EVN">
                  <templateId root="2.16.840.1.113883.3.88.11.83.8.1" />
                  <code code="73639000" displayName="Prescription Drug" codeSystem="2.16.840.1.113883.6.96" codeSystemName="SNOMED CT" />
                  <statusCode code="completed" />
                </observation>
              </entryRelationship>
            </substanceAdministration>
          </entry>
          <entry>
            <substanceAdministration moodCode="INT" classCode="SBADM">
              <templateId root="2.16.840.1.113883.3.88.11.83.8" assigningAuthorityName="HITSP C83" />
              <templateId root="2.16.840.1.113883.10.20.1.24" assigningAuthorityName="CCD" />
              <templateId root="1.3.6.1.4.1.19376.1.5.3.1.4.7" assigningAuthorityName="IHE PCC" />
              <templateId root="1.3.6.1.4.1.19376.1.5.3.1.4.7.1" assigningAuthorityName="IHE PCC" />
              <templateId root="2.16.840.1.113883.10.20.1.25" assigningAuthorityName="CCD" />
              <id root="6C0A7AC5-A85D-45FE-81E9-C8D07D894189" />
              <statusCode code="completed" />
              <effectiveTime xsi:type="IVL_TS">
                <low value="20121031131500" />
                <high nullFlavor="UNK" />
              </effectiveTime>
              <doseQuantity value="10" unit="mg/m2" />
              <consumable>
                <manufacturedProduct>
                  <templateId root="2.16.840.1.113883.3.88.11.83.8.2" assigningAuthorityName="HITSP C83" />
                  <templateId root="2.16.840.1.113883.10.20.1.53" />
                  <templateId root="1.3.6.1.4.1.19376.1.5.3.1.4.7.2" assigningAuthorityName="IHE PCC" />
                  <manufacturedMaterial>
                    <code code="16729-*108-11" displayName="mitomycin" codeSystemName="NDC" codeSystem="2.16.840.1.113883.6.69">
                      <originalText>
                        <reference value="#med-2" />
                      </originalText>
                    </code>
                    <name>mitomycin</name>
                  </manufacturedMaterial>
                </manufacturedProduct>
              </consumable>
              <entryRelationship typeCode="SUBJ">
                <observation classCode="OBS" moodCode="EVN">
                  <templateId root="2.16.840.1.113883.3.88.11.83.8.1" />
                  <code code="73639000" displayName="Prescription Drug" codeSystem="2.16.840.1.113883.6.96" codeSystemName="SNOMED CT" />
                  <statusCode code="completed" />
                </observation>
              </entryRelationship>
            </substanceAdministration>
          </entry>
        </section>
      </component>
      <component>
        <!--Advance Directive Section-->
        <section>
          <templateId root="2.16.840.1.113883.10.20.1.1" assigningAuthorityName="HL7 CCD" />
          <templateId root="2.16.840.1.113883.3.88.11.83.116" assigningAuthorityName="HITSP/C83" />
          <templateId root="1.3.6.1.4.1.19376.1.5.3.1.3.35" assigningAuthorityName="IHE PCC" />
          <templateId root="1.3.6.1.4.1.19376.1.5.3.1.3.34" assigningAuthorityName="IHE PCC" />
          <code code="42348-3" codeSystem="2.16.840.1.113883.6.1" codeSystemName="LOINC" />
          <title>Advance Directives</title>
          <text>
            <table border="1" width="100%">
              <thead>
                <tr>
                  <th>Directive</th>
                  <th>Description</th>
                  <th>Custodian</th>
                  <th>Status</th>
                </tr>
              </thead>
              <tbody>
                <tr>
                  <td>Intubation</td>
                  <td>
                    <content ID="AdvDir_1">Do not Intubation</content>
                  </td>
                  <td>Joel Wilkerson MD</td>
                  <td>Current and verified</td>
                </tr>
                <tr>
                  <td>Life Support</td>
                  <td>
                    <content ID="AdvDir_2">Do not Life Support</content>
                  </td>
                  <td>Joel Wilkerson MD</td>
                  <td>Verified With Family Only</td>
                </tr>
              </tbody>
            </table>
          </text>
          <entry typeCode="DRIV">
            <observation classCode="OBS" moodCode="EVN">
              <templateId root="2.16.840.1.113883.3.88.11.83.12" assigningAuthorityName="HITSP C83" />
              <templateId root="2.16.840.1.113883.10.20.1.17" assigningAuthorityName="CCD" />
              <templateId root="1.3.6.1.4.1.19376.1.5.3.1.4.13" assigningAuthorityName="IHE PCC" />
              <templateId root="1.3.6.1.4.1.19376.1.5.3.1.4.13.7" assigningAuthorityName="IHE PCC" />
              <id root="E87ABED3-3CF4-4AA4-8403-A48ABD5084AA" />
              <!--Advance directive observation template-->
              <code code="52765003" displayName="Intubation" codeSystem="2.16.840.1.113883.6.96" codeSystemName="SNOMED CT">
                <originalText>
                  <reference value="#AdvDir_1" />
                </originalText>
              </code>
              <text>
                <reference value="#AdvDir_1" />
              </text>
              <statusCode code="completed" />
              <effectiveTime nullFlavor="UNK">
                <low nullFlavor="UNK" />
                <high nullFlavor="NA" />
              </effectiveTime>
              <value xsi:type="BL" value="false" />
              <participant typeCode="CST">
                <participantRole classCode="AGNT">
                  <addr use="WP">
                    <streetAddressLine>6321 Lacey Drive</streetAddressLine>
                    <city>Lakewood</city>
                    <state>NY</state>
                    <postalCode>14750</postalCode>
                  </addr>
                  <telecom value="tel:+1-504-692-1745" use="WP" />
                  <playingEntity>
                    <name>Joel Wilkerson MD</name>
                  </playingEntity>
                </participantRole>
              </participant>
              <entryRelationship typeCode="REFR">
                <observation classCode="OBS" moodCode="EVN">
                  <templateId root="2.16.840.1.113883.10.20.1.37" />
                  <code code="33999-4" codeSystem="2.16.840.1.113883.6.1" codeSystemName="LOINC" displayName="Status" />
                  <statusCode code="completed" />
                  <value xsi:type="CE" code="425392003" codeSystem="2.16.840.1.113883.6.96" displayName="Current and verified" />
                </observation>
              </entryRelationship>
            </observation>
          </entry>
          <entry typeCode="DRIV">
            <observation classCode="OBS" moodCode="EVN">
              <templateId root="2.16.840.1.113883.3.88.11.83.12" assigningAuthorityName="HITSP C83" />
              <templateId root="2.16.840.1.113883.10.20.1.17" assigningAuthorityName="CCD" />
              <templateId root="1.3.6.1.4.1.19376.1.5.3.1.4.13" assigningAuthorityName="IHE PCC" />
              <templateId root="1.3.6.1.4.1.19376.1.5.3.1.4.13.7" assigningAuthorityName="IHE PCC" />
              <id root="0D195919-A32A-4F79-8D7E-E5411423BD9A" />
              <!--Advance directive observation template-->
              <code code="78823007" displayName="Life Support" codeSystem="2.16.840.1.113883.6.96" codeSystemName="SNOMED CT">
                <originalText>
                  <reference value="#AdvDir_2" />
                </originalText>
              </code>
              <text>
                <reference value="#AdvDir_2" />
              </text>
              <statusCode code="completed" />
              <effectiveTime nullFlavor="UNK">
                <low nullFlavor="UNK" />
                <high nullFlavor="NA" />
              </effectiveTime>
              <value xsi:type="BL" value="false" />
              <participant typeCode="CST">
                <participantRole classCode="AGNT">
                  <addr use="WP">
                    <streetAddressLine>6321 Lacey Drive</streetAddressLine>
                    <city>Lakewood</city>
                    <state>NY</state>
                    <postalCode>14750</postalCode>
                  </addr>
                  <telecom value="tel:+1-504-692-1745" use="WP" />
                  <playingEntity>
                    <name>Joel Wilkerson MD</name>
                  </playingEntity>
                </participantRole>
              </participant>
              <entryRelationship typeCode="REFR">
                <observation classCode="OBS" moodCode="EVN">
                  <templateId root="2.16.840.1.113883.10.20.1.37" />
                  <code code="33999-4" codeSystem="2.16.840.1.113883.6.1" codeSystemName="LOINC" displayName="Status" />
                  <statusCode code="completed" />
                  <value xsi:type="CE" code="425396000" codeSystem="2.16.840.1.113883.6.96" displayName="Verified With Family Only" />
                </observation>
              </entryRelationship>
            </observation>
          </entry>
        </section>
      </component>
    </structuredBody>
  </component>
</ClinicalDocument>